SyntenyQC/__init__.py
SyntenyQC/app.py
SyntenyQC/blast_functions.py
SyntenyQC/helpers.py
SyntenyQC/neighbourhood.py
SyntenyQC/networks.py
SyntenyQC/pipelines.py
SyntenyQC/visualisations.py
syntenyqc-2.0.dist-info/METADATA
syntenyqc-2.0.dist-info/WHEEL
syntenyqc-2.0.dist-info/entry_points.txt
syntenyqc-2.0.dist-info/licenses/LICENSE
syntenyqc-2.0.dist-info/RECORD
