Metadata-Version: 2.4
Name: SyntenyQC
Version: 2.0
Summary: A command line app for the pre-processing and quality control of synteny plot neighbourhoods
Project-URL: Homepage, https://github.com/Tim-Kirkwood/SyntenyQC
Project-URL: Issues, https://github.com/Tim-Kirkwood/SyntenyQC/issues
Author-email: Timothy Kirkwood <tdjkirkwood@hotmail.com>
Maintainer-email: Timothy Kirkwood <tdjkirkwood@hotmail.com>
License: MIT License
License-File: LICENSE
Keywords: bgc,biosynthetic gene cluster,genome neighbourhood,neighbourhood,synteny,synteny plot
Classifier: Development Status :: 4 - Beta
Classifier: Intended Audience :: Science/Research
Classifier: License :: OSI Approved :: MIT License
Classifier: Operating System :: OS Independent
Classifier: Programming Language :: Python :: 3
Classifier: Topic :: Scientific/Engineering :: Bio-Informatics
Requires-Python: <=3.12.9,>=3.10.0
Requires-Dist: biopython<=1.83,>=1.80
Requires-Dist: networkx<4.0.0,>=3.0.0
Requires-Dist: numpy>=1.24
Requires-Dist: pandas<3.0,>=2.0
Requires-Dist: plotly<7.0.0,>=6.0.0
Requires-Dist: scipy!=1.11.0,!=1.11.1,>=1.10
